README.md
setup.py
docums_localsearch.egg-info/PKG-INFO
docums_localsearch.egg-info/SOURCES.txt
docums_localsearch.egg-info/dependency_links.txt
docums_localsearch.egg-info/entry_points.txt
docums_localsearch.egg-info/requires.txt
docums_localsearch.egg-info/top_level.txt
docums_localsearch_plugin/__init__.py
docums_localsearch_plugin/plugin.py