Metadata-Version: 1.2
Name: docums-localsearch
Version: 1.0
Summary: A Docums plugin to replace the native "search" plugin with a search plugin that also works locally (file:// protocol). Only works with the Material theme.
Home-page: https://github.com/khanhduy1407/docums-localsearch
Author: NKDuy
Author-email: kn145660@gmail.com
License: MIT
Keywords: docums local search
Platform: UNKNOWN
Classifier: Development Status :: 4 - Beta
Classifier: Intended Audience :: Developers
Classifier: Intended Audience :: Information Technology
Classifier: License :: OSI Approved :: MIT License
Classifier: Programming Language :: Python
Classifier: Programming Language :: Python :: 3 :: Only
Classifier: Programming Language :: Python :: 3.4
Classifier: Programming Language :: Python :: 3.5
Classifier: Programming Language :: Python :: 3.6
Classifier: Programming Language :: Python :: 3.7
Requires-Python: >=3.5
